{"6":{"51":{"id":6,"num":36,"pourcentage":0.8508809626128062,"vote":99,"name":"القائمة التقدمية المستقلة"},"52":{"id":6,"num":36,"pourcentage":0.5519882843302917,"vote":49,"name":"القائمة التقدمية المستقلة"},"53":{"id":6,"num":36,"pourcentage":0.2810304449648712,"vote":18,"name":"القائمة التقدمية المستقلة"},"54":{"id":6,"num":36,"pourcentage":0.7621209664342468,"vote":47,"name":"القائمة التقدمية المستقلة"},"55":{"id":6,"num":36,"pourcentage":2.3055596089303956,"vote":158,"name":"القائمة التقدمية المستقلة"},"56":{"id":6,"num":36,"pourcentage":0.4699248120300752,"vote":20,"name":"القائمة التقدمية المستقلة"},"57":{"id":6,"num":36,"pourcentage":0.28030048211682923,"vote":25,"name":"القائمة التقدمية المستقلة"},"58":{"id":6,"num":36,"pourcentage":0.29416854127011594,"vote":17,"name":"القائمة التقدمية المستقلة"},"59":{"id":6,"num":36,"pourcentage":0.3868471953578337,"vote":14,"name":"القائمة التقدمية المستقلة"},"60":{"id":6,"num":36,"pourcentage":0.29331657238633985,"vote":14,"name":"القائمة التقدمية المستقلة"},"61":{"id":6,"num":36,"pourcentage":0.23249055507120026,"vote":8,"name":"القائمة التقدمية المستقلة"}},"35":{"51":{"id":35,"num":43,"pourcentage":0.730554361839278,"vote":85,"name":"قائمة أمل المستقلة"},"52":{"id":35,"num":43,"pourcentage":0.6421088205474822,"vote":57,"name":"قائمة أمل المستقلة"},"53":{"id":35,"num":43,"pourcentage":0.6713505074160812,"vote":43,"name":"قائمة أمل المستقلة"},"54":{"id":35,"num":43,"pourcentage":0.697259607588779,"vote":43,"name":"قائمة أمل المستقلة"},"55":{"id":35,"num":43,"pourcentage":0.6274624252152342,"vote":43,"name":"قائمة أمل المستقلة"},"56":{"id":35,"num":43,"pourcentage":0.7048872180451128,"vote":30,"name":"قائمة أمل المستقلة"},"57":{"id":35,"num":43,"pourcentage":0.9418096199125462,"vote":84,"name":"قائمة أمل المستقلة"},"58":{"id":35,"num":43,"pourcentage":3.9280152275480185,"vote":227,"name":"قائمة أمل المستقلة"},"59":{"id":35,"num":43,"pourcentage":0.7184305056645481,"vote":26,"name":"قائمة أمل المستقلة"},"60":{"id":35,"num":43,"pourcentage":0.5656819610307983,"vote":27,"name":"قائمة أمل المستقلة"},"61":{"id":35,"num":43,"pourcentage":0.34873583260680036,"vote":12,"name":"قائمة أمل المستقلة"}},"49":{"51":{"id":49,"num":3,"pourcentage":0.4383326171035668,"vote":51,"name":"قائمة ائتلاف الأمة"},"52":{"id":49,"num":3,"pourcentage":0.7434944237918215,"vote":66,"name":"قائمة ائتلاف الأمة"},"53":{"id":49,"num":3,"pourcentage":1.0304449648711944,"vote":66,"name":"قائمة ائتلاف الأمة"},"54":{"id":49,"num":3,"pourcentage":0.5675368898978433,"vote":35,"name":"قائمة ائتلاف الأمة"},"55":{"id":49,"num":3,"pourcentage":0.437764482708303,"vote":30,"name":"قائمة ائتلاف الأمة"},"56":{"id":49,"num":3,"pourcentage":0.6578947368421052,"vote":28,"name":"قائمة ائتلاف الأمة"},"57":{"id":49,"num":3,"pourcentage":2.1414956833725753,"vote":191,"name":"قائمة ائتلاف الأمة"},"58":{"id":49,"num":3,"pourcentage":0.7613774009344177,"vote":44,"name":"قائمة ائتلاف الأمة"},"59":{"id":49,"num":3,"pourcentage":1.3263332412268583,"vote":48,"name":"قائمة ائتلاف الأمة"},"60":{"id":49,"num":3,"pourcentage":0.7332914309658495,"vote":35,"name":"قائمة ائتلاف الأمة"},"61":{"id":49,"num":3,"pourcentage":0.2034292356873002,"vote":7,"name":"قائمة ائتلاف الأمة"}},"74":{"51":{"id":74,"num":39,"pourcentage":0.5672539750752041,"vote":66,"name":"قائمة الإرادة من أجل التنمية"},"52":{"id":74,"num":39,"pourcentage":0.9124704291990536,"vote":81,"name":"قائمة الإرادة من أجل التنمية"},"53":{"id":74,"num":39,"pourcentage":0.4215456674473068,"vote":27,"name":"قائمة الإرادة من أجل التنمية"},"54":{"id":74,"num":39,"pourcentage":0.3729528133614399,"vote":23,"name":"قائمة الإرادة من أجل التنمية"},"55":{"id":74,"num":39,"pourcentage":0.4669487815555231,"vote":32,"name":"قائمة الإرادة من أجل التنمية"},"56":{"id":74,"num":39,"pourcentage":0.42293233082706766,"vote":18,"name":"قائمة الإرادة من أجل التنمية"},"57":{"id":74,"num":39,"pourcentage":0.30272452068617556,"vote":27,"name":"قائمة الإرادة من أجل التنمية"},"58":{"id":74,"num":39,"pourcentage":0.4499048278248832,"vote":26,"name":"قائمة الإرادة من أجل التنمية"},"59":{"id":74,"num":39,"pourcentage":0.5526388505111909,"vote":20,"name":"قائمة الإرادة من أجل التنمية"},"60":{"id":74,"num":39,"pourcentage":0.5237795935470354,"vote":25,"name":"قائمة الإرادة من أجل التنمية"},"61":{"id":74,"num":39,"pourcentage":0.17436791630340018,"vote":6,"name":"قائمة الإرادة من أجل التنمية"}},"81":{"51":{"id":81,"num":41,"pourcentage":0.45552213149978515,"vote":53,"name":"قائمة الإصلاح والتنمية"},"52":{"id":81,"num":41,"pourcentage":0.6083136194660358,"vote":54,"name":"قائمة الإصلاح والتنمية"},"53":{"id":81,"num":41,"pourcentage":0.32786885245901637,"vote":21,"name":"قائمة الإصلاح والتنمية"},"54":{"id":81,"num":41,"pourcentage":0.6323982487433112,"vote":39,"name":"قائمة الإصلاح والتنمية"},"55":{"id":81,"num":41,"pourcentage":0.437764482708303,"vote":30,"name":"قائمة الإصلاح والتنمية"},"56":{"id":81,"num":41,"pourcentage":0.21146616541353383,"vote":9,"name":"قائمة الإصلاح والتنمية"},"57":{"id":81,"num":41,"pourcentage":2.7581567440295998,"vote":246,"name":"قائمة الإصلاح والتنمية"},"58":{"id":81,"num":41,"pourcentage":0.9863298148468593,"vote":57,"name":"قائمة الإصلاح والتنمية"},"59":{"id":81,"num":41,"pourcentage":0.303951367781155,"vote":11,"name":"قائمة الإصلاح والتنمية"},"60":{"id":81,"num":41,"pourcentage":0.7332914309658495,"vote":35,"name":"قائمة الإصلاح والتنمية"},"61":{"id":81,"num":41,"pourcentage":0.14530659691950015,"vote":5,"name":"قائمة الإصلاح والتنمية"}},"85":{"51":{"id":85,"num":13,"pourcentage":1.0915341641598626,"vote":127,"name":"قائمة الإتحاد الديمقراطي الوحدوي"},"52":{"id":85,"num":13,"pourcentage":0.9687957643347977,"vote":86,"name":"قائمة الإتحاد الديمقراطي الوحدوي"},"53":{"id":85,"num":13,"pourcentage":2.9508196721311477,"vote":189,"name":"قائمة الإتحاد الديمقراطي الوحدوي"},"54":{"id":85,"num":13,"pourcentage":2.3187935787254745,"vote":143,"name":"قائمة الإتحاد الديمقراطي الوحدوي"},"55":{"id":85,"num":13,"pourcentage":1.357069896395739,"vote":93,"name":"قائمة الإتحاد الديمقراطي الوحدوي"},"56":{"id":85,"num":13,"pourcentage":2.138157894736842,"vote":91,"name":"قائمة الإتحاد الديمقراطي الوحدوي"},"57":{"id":85,"num":13,"pourcentage":1.0427177934746048,"vote":93,"name":"قائمة الإتحاد الديمقراطي الوحدوي"},"58":{"id":85,"num":13,"pourcentage":0.9863298148468593,"vote":57,"name":"قائمة الإتحاد الديمقراطي الوحدوي"},"59":{"id":85,"num":13,"pourcentage":1.3815971262779774,"vote":50,"name":"قائمة الإتحاد الديمقراطي الوحدوي"},"60":{"id":85,"num":13,"pourcentage":1.8227529855436833,"vote":87,"name":"قائمة الإتحاد الديمقراطي الوحدوي"},"61":{"id":85,"num":13,"pourcentage":7.236268526591107,"vote":249,"name":"قائمة الإتحاد الديمقراطي الوحدوي"}},"87":{"51":{"id":87,"num":6,"pourcentage":1.2548345509239363,"vote":146,"name":"قائمة الائتلاف الديمقراطي المستقل طريق السلامة"},"52":{"id":87,"num":6,"pourcentage":2.0727723329953816,"vote":184,"name":"قائمة الائتلاف الديمقراطي المستقل طريق السلامة"},"53":{"id":87,"num":6,"pourcentage":1.2021857923497268,"vote":77,"name":"قائمة الائتلاف الديمقراطي المستقل طريق السلامة"},"54":{"id":87,"num":6,"pourcentage":1.1188584400843198,"vote":69,"name":"قائمة الائتلاف الديمقراطي المستقل طريق السلامة"},"55":{"id":87,"num":6,"pourcentage":0.9047132642638261,"vote":62,"name":"قائمة الائتلاف الديمقراطي المستقل طريق السلامة"},"56":{"id":87,"num":6,"pourcentage":1.0338345864661653,"vote":44,"name":"قائمة الائتلاف الديمقراطي المستقل طريق السلامة"},"57":{"id":87,"num":6,"pourcentage":0.526964906379639,"vote":47,"name":"قائمة الائتلاف الديمقراطي المستقل طريق السلامة"},"58":{"id":87,"num":6,"pourcentage":1.6438830247447653,"vote":95,"name":"قائمة الائتلاف الديمقراطي المستقل طريق السلامة"},"59":{"id":87,"num":6,"pourcentage":1.0776457584968222,"vote":39,"name":"قائمة الائتلاف الديمقراطي المستقل طريق السلامة"},"60":{"id":87,"num":6,"pourcentage":0.7751937984496124,"vote":37,"name":"قائمة الائتلاف الديمقراطي المستقل طريق السلامة"},"61":{"id":87,"num":6,"pourcentage":0.5521650682941005,"vote":19,"name":"قائمة الائتلاف الديمقراطي المستقل طريق السلامة"}},"91":{"51":{"id":91,"num":35,"pourcentage":0.44692737430167595,"vote":52,"name":"قائمة الازدهار والتقدم"},"52":{"id":91,"num":35,"pourcentage":0.3041568097330179,"vote":27,"name":"قائمة الازدهار والتقدم"},"53":{"id":91,"num":35,"pourcentage":0.18735362997658078,"vote":12,"name":"قائمة الازدهار والتقدم"},"54":{"id":91,"num":35,"pourcentage":0.2756607750932382,"vote":17,"name":"قائمة الازدهار والتقدم"},"55":{"id":91,"num":35,"pourcentage":0.26265868962498173,"vote":18,"name":"قائمة الازدهار والتقدم"},"56":{"id":91,"num":35,"pourcentage":0.5169172932330827,"vote":22,"name":"قائمة الازدهار والتقدم"},"57":{"id":91,"num":35,"pourcentage":0.16818028927009754,"vote":15,"name":"قائمة الازدهار والتقدم"},"58":{"id":91,"num":35,"pourcentage":0.207648382073023,"vote":12,"name":"قائمة الازدهار والتقدم"},"59":{"id":91,"num":35,"pourcentage":0.27631942525559544,"vote":10,"name":"قائمة الازدهار والتقدم"},"60":{"id":91,"num":35,"pourcentage":0.2723653886444584,"vote":13,"name":"قائمة الازدهار والتقدم"},"61":{"id":91,"num":35,"pourcentage":0.2034292356873002,"vote":7,"name":"قائمة الازدهار والتقدم"}},"96":{"51":{"id":96,"num":7,"pourcentage":5.002148689299527,"vote":582,"name":"قائمة الاتحاد الوطني الحر"},"52":{"id":96,"num":7,"pourcentage":6.229582066013293,"vote":553,"name":"قائمة الاتحاد الوطني الحر"},"53":{"id":96,"num":7,"pourcentage":7.197501951600311,"vote":461,"name":"قائمة الاتحاد الوطني الحر"},"54":{"id":96,"num":7,"pourcentage":4.864601913410086,"vote":300,"name":"قائمة الاتحاد الوطني الحر"},"55":{"id":96,"num":7,"pourcentage":4.611119217860791,"vote":316,"name":"قائمة الاتحاد الوطني الحر"},"56":{"id":96,"num":7,"pourcentage":3.9943609022556394,"vote":170,"name":"قائمة الاتحاد الوطني الحر"},"57":{"id":96,"num":7,"pourcentage":11.57080390178271,"vote":1032,"name":"قائمة الاتحاد الوطني الحر"},"58":{"id":96,"num":7,"pourcentage":6.662052258176156,"vote":385,"name":"قائمة الاتحاد الوطني الحر"},"59":{"id":96,"num":7,"pourcentage":7.211936999171041,"vote":261,"name":"قائمة الاتحاد الوطني الحر"},"60":{"id":96,"num":7,"pourcentage":4.043578462183113,"vote":193,"name":"قائمة الاتحاد الوطني الحر"},"61":{"id":96,"num":7,"pourcentage":5.899447834931705,"vote":203,"name":"قائمة الاتحاد الوطني الحر"}},"115":{"51":{"id":115,"num":34,"pourcentage":0.5414697034808766,"vote":63,"name":"قائمة الجبهة الشعبية الوحدوية"},"52":{"id":115,"num":34,"pourcentage":0.653373887574631,"vote":58,"name":"قائمة الجبهة الشعبية الوحدوية"},"53":{"id":115,"num":34,"pourcentage":0.7494145199063231,"vote":48,"name":"قائمة الجبهة الشعبية الوحدوية"},"54":{"id":115,"num":34,"pourcentage":0.6323982487433112,"vote":39,"name":"قائمة الجبهة الشعبية الوحدوية"},"55":{"id":115,"num":34,"pourcentage":0.6274624252152342,"vote":43,"name":"قائمة الجبهة الشعبية الوحدوية"},"56":{"id":115,"num":34,"pourcentage":0.6578947368421052,"vote":28,"name":"قائمة الجبهة الشعبية الوحدوية"},"57":{"id":115,"num":34,"pourcentage":0.8969615427738535,"vote":80,"name":"قائمة الجبهة الشعبية الوحدوية"},"58":{"id":115,"num":34,"pourcentage":0.9517217511680223,"vote":55,"name":"قائمة الجبهة الشعبية الوحدوية"},"59":{"id":115,"num":34,"pourcentage":0.9947499309201437,"vote":36,"name":"قائمة الجبهة الشعبية الوحدوية"},"60":{"id":115,"num":34,"pourcentage":0.6075843285145611,"vote":29,"name":"قائمة الجبهة الشعبية الوحدوية"},"61":{"id":115,"num":34,"pourcentage":0.5521650682941005,"vote":19,"name":"قائمة الجبهة الشعبية الوحدوية"}},"136":{"51":{"id":136,"num":44,"pourcentage":0.35238504512247526,"vote":41,"name":"قائمة الحزب الدستوري الجديد"},"52":{"id":136,"num":44,"pourcentage":0.2816266756787203,"vote":25,"name":"قائمة الحزب الدستوري الجديد"},"53":{"id":136,"num":44,"pourcentage":0.312256049960968,"vote":20,"name":"قائمة الحزب الدستوري الجديد"},"54":{"id":136,"num":44,"pourcentage":0.2432300956705043,"vote":15,"name":"قائمة الحزب الدستوري الجديد"},"55":{"id":136,"num":44,"pourcentage":1.036042609076317,"vote":71,"name":"قائمة الحزب الدستوري الجديد"},"56":{"id":136,"num":44,"pourcentage":0.2349624060150376,"vote":10,"name":"قائمة الحزب الدستوري الجديد"},"57":{"id":136,"num":44,"pourcentage":0.20181634712411706,"vote":18,"name":"قائمة الحزب الدستوري الجديد"},"58":{"id":136,"num":44,"pourcentage":1.920747534175463,"vote":111,"name":"قائمة الحزب الدستوري الجديد"},"59":{"id":136,"num":44,"pourcentage":0.16579165515335728,"vote":6,"name":"قائمة الحزب الدستوري الجديد"},"60":{"id":136,"num":44,"pourcentage":0.18856065367693275,"vote":9,"name":"قائمة الحزب الدستوري الجديد"},"61":{"id":136,"num":44,"pourcentage":0.2034292356873002,"vote":7,"name":"قائمة الحزب الدستوري الجديد"}},"137":{"51":{"id":137,"num":37,"pourcentage":8.036097980232059,"vote":935,"name":"قائمة الحزب الديمقراطي التقدمي"},"52":{"id":137,"num":37,"pourcentage":5.328376703841388,"vote":473,"name":"قائمة الحزب الديمقراطي التقدمي"},"53":{"id":137,"num":37,"pourcentage":5.714285714285714,"vote":366,"name":"قائمة الحزب الديمقراطي التقدمي"},"54":{"id":137,"num":37,"pourcentage":3.551159396789363,"vote":219,"name":"قائمة الحزب الديمقراطي التقدمي"},"55":{"id":137,"num":37,"pourcentage":4.830001459214942,"vote":331,"name":"قائمة الحزب الديمقراطي التقدمي"},"56":{"id":137,"num":37,"pourcentage":3.547932330827068,"vote":151,"name":"قائمة الحزب الديمقراطي التقدمي"},"57":{"id":137,"num":37,"pourcentage":2.4666442426280972,"vote":220,"name":"قائمة الحزب الديمقراطي التقدمي"},"58":{"id":137,"num":37,"pourcentage":4.897041010555459,"vote":283,"name":"قائمة الحزب الديمقراطي التقدمي"},"59":{"id":137,"num":37,"pourcentage":6.742193976236529,"vote":244,"name":"قائمة الحزب الديمقراطي التقدمي"},"60":{"id":137,"num":37,"pourcentage":4.043578462183113,"vote":193,"name":"قائمة الحزب الديمقراطي التقدمي"},"61":{"id":137,"num":37,"pourcentage":2.6155187445510024,"vote":90,"name":"قائمة الحزب الديمقراطي التقدمي"}},"156":{"51":{"id":156,"num":16,"pourcentage":0.730554361839278,"vote":85,"name":"قائمة الخير المستقلة"},"52":{"id":156,"num":16,"pourcentage":0.9124704291990536,"vote":81,"name":"قائمة الخير المستقلة"},"53":{"id":156,"num":16,"pourcentage":0.37470725995316156,"vote":24,"name":"قائمة الخير المستقلة"},"54":{"id":156,"num":16,"pourcentage":0.5351062104751094,"vote":33,"name":"قائمة الخير المستقلة"},"55":{"id":156,"num":16,"pourcentage":0.7733839194513352,"vote":53,"name":"قائمة الخير المستقلة"},"56":{"id":156,"num":16,"pourcentage":4.722744360902255,"vote":201,"name":"قائمة الخير المستقلة"},"57":{"id":156,"num":16,"pourcentage":1.2669581791680682,"vote":113,"name":"قائمة الخير المستقلة"},"58":{"id":156,"num":16,"pourcentage":1.038241910365115,"vote":60,"name":"قائمة الخير المستقلة"},"59":{"id":156,"num":16,"pourcentage":1.21580547112462,"vote":44,"name":"قائمة الخير المستقلة"},"60":{"id":156,"num":16,"pourcentage":0.7332914309658495,"vote":35,"name":"قائمة الخير المستقلة"},"61":{"id":156,"num":16,"pourcentage":0.4649811101424005,"vote":16,"name":"قائمة الخير المستقلة"}},"160":{"51":{"id":160,"num":29,"pourcentage":0.6016330038676407,"vote":70,"name":"قائمة الديمقراطية والعدالة الاجتماعية"},"52":{"id":160,"num":29,"pourcentage":0.597048552438887,"vote":53,"name":"قائمة الديمقراطية والعدالة الاجتماعية"},"53":{"id":160,"num":29,"pourcentage":0.5152224824355972,"vote":33,"name":"قائمة الديمقراطية والعدالة الاجتماعية"},"54":{"id":160,"num":29,"pourcentage":0.6648289281660451,"vote":41,"name":"قائمة الديمقراطية والعدالة الاجتماعية"},"55":{"id":160,"num":29,"pourcentage":1.0798190573471473,"vote":74,"name":"قائمة الديمقراطية والعدالة الاجتماعية"},"56":{"id":160,"num":29,"pourcentage":0.5639097744360901,"vote":24,"name":"قائمة الديمقراطية والعدالة الاجتماعية"},"57":{"id":160,"num":29,"pourcentage":2.119071644803229,"vote":189,"name":"قائمة الديمقراطية والعدالة الاجتماعية"},"58":{"id":160,"num":29,"pourcentage":8.548191728672782,"vote":494,"name":"قائمة الديمقراطية والعدالة الاجتماعية"},"59":{"id":160,"num":29,"pourcentage":0.9394860458690245,"vote":34,"name":"قائمة الديمقراطية والعدالة الاجتماعية"},"60":{"id":160,"num":29,"pourcentage":0.4818772260632726,"vote":23,"name":"قائمة الديمقراطية والعدالة الاجتماعية"},"61":{"id":160,"num":29,"pourcentage":0.31967451322290036,"vote":11,"name":"قائمة الديمقراطية والعدالة الاجتماعية"}},"184":{"51":{"id":184,"num":28,"pourcentage":0.618822518263859,"vote":72,"name":"قائمة الشعب أراد الحياة"},"52":{"id":184,"num":28,"pourcentage":0.5294581502759942,"vote":47,"name":"قائمة الشعب أراد الحياة"},"53":{"id":184,"num":28,"pourcentage":0.3434816549570648,"vote":22,"name":"قائمة الشعب أراد الحياة"},"54":{"id":184,"num":28,"pourcentage":0.5837522296092104,"vote":36,"name":"قائمة الشعب أراد الحياة"},"55":{"id":184,"num":28,"pourcentage":0.5107252298263534,"vote":35,"name":"قائمة الشعب أراد الحياة"},"56":{"id":184,"num":28,"pourcentage":11.56015037593985,"vote":492,"name":"قائمة الشعب أراد الحياة"},"57":{"id":184,"num":28,"pourcentage":0.20181634712411706,"vote":18,"name":"قائمة الشعب أراد الحياة"},"58":{"id":184,"num":28,"pourcentage":0.4326007959854646,"vote":25,"name":"قائمة الشعب أراد الحياة"},"59":{"id":184,"num":28,"pourcentage":0.49737496546007187,"vote":18,"name":"قائمة الشعب أراد الحياة"},"60":{"id":184,"num":28,"pourcentage":0.6285355122564426,"vote":30,"name":"قائمة الشعب أراد الحياة"},"61":{"id":184,"num":28,"pourcentage":0.17436791630340018,"vote":6,"name":"قائمة الشعب أراد الحياة"}},"205":{"51":{"id":205,"num":26,"pourcentage":0.730554361839278,"vote":85,"name":"قائمة التآلف الجمهوري"},"52":{"id":205,"num":26,"pourcentage":0.5632533513574406,"vote":50,"name":"قائمة التآلف الجمهوري"},"53":{"id":205,"num":26,"pourcentage":0.4215456674473068,"vote":27,"name":"قائمة التآلف الجمهوري"},"54":{"id":205,"num":26,"pourcentage":1.7836873682503647,"vote":110,"name":"قائمة التآلف الجمهوري"},"55":{"id":205,"num":26,"pourcentage":0.5836859769444039,"vote":40,"name":"قائمة التآلف الجمهوري"},"56":{"id":205,"num":26,"pourcentage":0.7283834586466165,"vote":31,"name":"قائمة التآلف الجمهوري"},"57":{"id":205,"num":26,"pourcentage":0.4821168292409463,"vote":43,"name":"قائمة التآلف الجمهوري"},"58":{"id":205,"num":26,"pourcentage":0.4499048278248832,"vote":26,"name":"قائمة التآلف الجمهوري"},"59":{"id":205,"num":26,"pourcentage":0.5526388505111909,"vote":20,"name":"قائمة التآلف الجمهوري"},"60":{"id":205,"num":26,"pourcentage":1.0685103708359522,"vote":51,"name":"قائمة التآلف الجمهوري"},"61":{"id":205,"num":26,"pourcentage":0.8137169427492008,"vote":28,"name":"قائمة التآلف الجمهوري"}},"259":{"51":{"id":259,"num":46,"pourcentage":2.758917060593038,"vote":321,"name":"قائمة القطب الديمقراطي الحداثي"},"52":{"id":259,"num":46,"pourcentage":2.3431339416469528,"vote":208,"name":"قائمة القطب الديمقراطي الحداثي"},"53":{"id":259,"num":46,"pourcentage":0.9211553473848557,"vote":59,"name":"قائمة القطب الديمقراطي الحداثي"},"54":{"id":259,"num":46,"pourcentage":1.1512891195070536,"vote":71,"name":"قائمة القطب الديمقراطي الحداثي"},"55":{"id":259,"num":46,"pourcentage":1.663505034291551,"vote":114,"name":"قائمة القطب الديمقراطي الحداثي"},"56":{"id":259,"num":46,"pourcentage":1.0338345864661653,"vote":44,"name":"قائمة القطب الديمقراطي الحداثي"},"57":{"id":259,"num":46,"pourcentage":1.513622603430878,"vote":135,"name":"قائمة القطب الديمقراطي الحداثي"},"58":{"id":259,"num":46,"pourcentage":1.245890292438138,"vote":72,"name":"قائمة القطب الديمقراطي الحداثي"},"59":{"id":259,"num":46,"pourcentage":1.2710693561757391,"vote":46,"name":"قائمة القطب الديمقراطي الحداثي"},"60":{"id":259,"num":46,"pourcentage":1.2989733919966477,"vote":62,"name":"قائمة القطب الديمقراطي الحداثي"},"61":{"id":259,"num":46,"pourcentage":0.7846556233653008,"vote":27,"name":"قائمة القطب الديمقراطي الحداثي"}},"264":{"51":{"id":264,"num":8,"pourcentage":0.36097980232058446,"vote":42,"name":"قائمة الكرامة"},"52":{"id":264,"num":8,"pourcentage":0.5181930832488454,"vote":46,"name":"قائمة الكرامة"},"53":{"id":264,"num":8,"pourcentage":1.2021857923497268,"vote":77,"name":"قائمة الكرامة"},"54":{"id":264,"num":8,"pourcentage":0.40538349278417385,"vote":25,"name":"قائمة الكرامة"},"55":{"id":264,"num":8,"pourcentage":0.42317233328469284,"vote":29,"name":"قائمة الكرامة"},"56":{"id":264,"num":8,"pourcentage":0.39943609022556387,"vote":17,"name":"قائمة الكرامة"},"57":{"id":264,"num":8,"pourcentage":0.44848077138692677,"vote":40,"name":"قائمة الكرامة"},"58":{"id":264,"num":8,"pourcentage":0.3633846686277903,"vote":21,"name":"قائمة الكرامة"},"59":{"id":264,"num":8,"pourcentage":1.1329096435479415,"vote":41,"name":"قائمة الكرامة"},"60":{"id":264,"num":8,"pourcentage":0.8380473496752567,"vote":40,"name":"قائمة الكرامة"},"61":{"id":264,"num":8,"pourcentage":0.4359197907585004,"vote":15,"name":"قائمة الكرامة"}},"282":{"51":{"id":282,"num":33,"pourcentage":1.5298667812634292,"vote":178,"name":"قائمة المسار التنموي العادل"},"52":{"id":282,"num":33,"pourcentage":1.926326461642447,"vote":171,"name":"قائمة المسار التنموي العادل"},"53":{"id":282,"num":33,"pourcentage":0.39032006245121,"vote":25,"name":"قائمة المسار التنموي العادل"},"54":{"id":282,"num":33,"pourcentage":0.7621209664342468,"vote":47,"name":"قائمة المسار التنموي العادل"},"55":{"id":282,"num":33,"pourcentage":0.11673719538888078,"vote":8,"name":"قائمة المسار التنموي العادل"},"56":{"id":282,"num":33,"pourcentage":0.4464285714285714,"vote":19,"name":"قائمة المسار التنموي العادل"},"57":{"id":282,"num":33,"pourcentage":0.3812086556788878,"vote":34,"name":"قائمة المسار التنموي العادل"},"58":{"id":282,"num":33,"pourcentage":1.418930610832324,"vote":82,"name":"قائمة المسار التنموي العادل"},"59":{"id":282,"num":33,"pourcentage":0.46974302293451226,"vote":17,"name":"قائمة المسار التنموي العادل"},"60":{"id":282,"num":33,"pourcentage":0.5447307772889168,"vote":26,"name":"قائمة المسار التنموي العادل"},"61":{"id":282,"num":33,"pourcentage":0.14530659691950015,"vote":5,"name":"قائمة المسار التنموي العادل"}},"348":{"51":{"id":348,"num":23,"pourcentage":2.1744735711216157,"vote":253,"name":"قائمة الوفاء "},"52":{"id":348,"num":23,"pourcentage":2.0164469978596373,"vote":179,"name":"قائمة الوفاء "},"53":{"id":348,"num":23,"pourcentage":0.32786885245901637,"vote":21,"name":"قائمة الوفاء "},"54":{"id":348,"num":23,"pourcentage":0.5837522296092104,"vote":36,"name":"قائمة الوفاء "},"55":{"id":348,"num":23,"pourcentage":0.5836859769444039,"vote":40,"name":"قائمة الوفاء "},"56":{"id":348,"num":23,"pourcentage":0.5169172932330827,"vote":22,"name":"قائمة الوفاء "},"57":{"id":348,"num":23,"pourcentage":0.3363605785401951,"vote":30,"name":"قائمة الوفاء "},"58":{"id":348,"num":23,"pourcentage":1.0901540058833707,"vote":63,"name":"قائمة الوفاء "},"59":{"id":348,"num":23,"pourcentage":0.5526388505111909,"vote":20,"name":"قائمة الوفاء "},"60":{"id":348,"num":23,"pourcentage":0.9847056358684266,"vote":47,"name":"قائمة الوفاء "},"61":{"id":348,"num":23,"pourcentage":0.3777971519907004,"vote":13,"name":"قائمة الوفاء "}},"377":{"51":{"id":377,"num":15,"pourcentage":1.1688869789428449,"vote":136,"name":"قائمة حركة البعث"},"52":{"id":377,"num":15,"pourcentage":1.0363861664976908,"vote":92,"name":"قائمة حركة البعث"},"53":{"id":377,"num":15,"pourcentage":1.3427010148321623,"vote":86,"name":"قائمة حركة البعث"},"54":{"id":377,"num":15,"pourcentage":0.729690287011513,"vote":45,"name":"قائمة حركة البعث"},"55":{"id":377,"num":15,"pourcentage":1.181964103312418,"vote":81,"name":"قائمة حركة البعث"},"56":{"id":377,"num":15,"pourcentage":0.9163533834586466,"vote":39,"name":"قائمة حركة البعث"},"57":{"id":377,"num":15,"pourcentage":1.1436259670366633,"vote":102,"name":"قائمة حركة البعث"},"58":{"id":377,"num":15,"pourcentage":0.709465305416162,"vote":41,"name":"قائمة حركة البعث"},"59":{"id":377,"num":15,"pourcentage":1.409229068803537,"vote":51,"name":"قائمة حركة البعث"},"60":{"id":377,"num":15,"pourcentage":1.5294364131573435,"vote":73,"name":"قائمة حركة البعث"},"61":{"id":377,"num":15,"pourcentage":0.49404242952630045,"vote":17,"name":"قائمة حركة البعث"}},"381":{"51":{"id":381,"num":31,"pourcentage":0.6532015470562956,"vote":76,"name":"قائمة حركة الديمقراطية والتنمية"},"52":{"id":381,"num":31,"pourcentage":0.7660245578461191,"vote":68,"name":"قائمة حركة الديمقراطية والتنمية"},"53":{"id":381,"num":31,"pourcentage":0.4996096799375488,"vote":32,"name":"قائمة حركة الديمقراطية والتنمية"},"54":{"id":381,"num":31,"pourcentage":1.5404572725798604,"vote":95,"name":"قائمة حركة الديمقراطية والتنمية"},"55":{"id":381,"num":31,"pourcentage":0.4961330804027433,"vote":34,"name":"قائمة حركة الديمقراطية والتنمية"},"56":{"id":381,"num":31,"pourcentage":0.9868421052631579,"vote":42,"name":"قائمة حركة الديمقراطية والتنمية"},"57":{"id":381,"num":31,"pourcentage":0.3363605785401951,"vote":30,"name":"قائمة حركة الديمقراطية والتنمية"},"58":{"id":381,"num":31,"pourcentage":1.1074580377227894,"vote":64,"name":"قائمة حركة الديمقراطية والتنمية"},"59":{"id":381,"num":31,"pourcentage":0.41447913788339324,"vote":15,"name":"قائمة حركة الديمقراطية والتنمية"},"60":{"id":381,"num":31,"pourcentage":0.3771213073538655,"vote":18,"name":"قائمة حركة الديمقراطية والتنمية"},"61":{"id":381,"num":31,"pourcentage":1.3949433304272014,"vote":48,"name":"قائمة حركة الديمقراطية والتنمية"}},"382":{"51":{"id":382,"num":14,"pourcentage":0.5930382466695315,"vote":69,"name":"قائمة حركة الديمقراطيين الاشتراكيين"},"52":{"id":382,"num":14,"pourcentage":0.5407232173031429,"vote":48,"name":"قائمة حركة الديمقراطيين الاشتراكيين"},"53":{"id":382,"num":14,"pourcentage":0.5932864949258392,"vote":38,"name":"قائمة حركة الديمقراطيين الاشتراكيين"},"54":{"id":382,"num":14,"pourcentage":1.1350737797956867,"vote":70,"name":"قائمة حركة الديمقراطيين الاشتراكيين"},"55":{"id":382,"num":14,"pourcentage":0.5399095286735737,"vote":37,"name":"قائمة حركة الديمقراطيين الاشتراكيين"},"56":{"id":382,"num":14,"pourcentage":0.6343984962406015,"vote":27,"name":"قائمة حركة الديمقراطيين الاشتراكيين"},"57":{"id":382,"num":14,"pourcentage":0.6278730799416975,"vote":56,"name":"قائمة حركة الديمقراطيين الاشتراكيين"},"58":{"id":382,"num":14,"pourcentage":0.6575532098979062,"vote":38,"name":"قائمة حركة الديمقراطيين الاشتراكيين"},"59":{"id":382,"num":14,"pourcentage":0.3868471953578337,"vote":14,"name":"قائمة حركة الديمقراطيين الاشتراكيين"},"60":{"id":382,"num":14,"pourcentage":1.1313639220615965,"vote":54,"name":"قائمة حركة الديمقراطيين الاشتراكيين"},"61":{"id":382,"num":14,"pourcentage":0.9009009009009009,"vote":31,"name":"قائمة حركة الديمقراطيين الاشتراكيين"}},"386":{"51":{"id":386,"num":32,"pourcentage":1.2978083369144822,"vote":151,"name":"قائمة حركة الشعب"},"52":{"id":386,"num":32,"pourcentage":0.8561450940633097,"vote":76,"name":"قائمة حركة الشعب"},"53":{"id":386,"num":32,"pourcentage":0.234192037470726,"vote":15,"name":"قائمة حركة الشعب"},"54":{"id":386,"num":32,"pourcentage":0.2432300956705043,"vote":15,"name":"قائمة حركة الشعب"},"55":{"id":386,"num":32,"pourcentage":0.6712388734860645,"vote":46,"name":"قائمة حركة الشعب"},"56":{"id":386,"num":32,"pourcentage":2.6785714285714284,"vote":114,"name":"قائمة حركة الشعب"},"57":{"id":386,"num":32,"pourcentage":0.22424038569346338,"vote":20,"name":"قائمة حركة الشعب"},"58":{"id":386,"num":32,"pourcentage":0.9863298148468593,"vote":57,"name":"قائمة حركة الشعب"},"59":{"id":386,"num":32,"pourcentage":0.35921525283227407,"vote":13,"name":"قائمة حركة الشعب"},"60":{"id":386,"num":32,"pourcentage":1.0475591870940708,"vote":50,"name":"قائمة حركة الشعب"},"61":{"id":386,"num":32,"pourcentage":0.34873583260680036,"vote":12,"name":"قائمة حركة الشعب"}},"387":{"51":{"id":387,"num":45,"pourcentage":3.5754189944134076,"vote":416,"name":"قائمة حركة الشعب الوحدوية التقدمية"},"52":{"id":387,"num":45,"pourcentage":2.3994592767826965,"vote":213,"name":"قائمة حركة الشعب الوحدوية التقدمية"},"53":{"id":387,"num":45,"pourcentage":0.312256049960968,"vote":20,"name":"قائمة حركة الشعب الوحدوية التقدمية"},"54":{"id":387,"num":45,"pourcentage":1.362088535754824,"vote":84,"name":"قائمة حركة الشعب الوحدوية التقدمية"},"55":{"id":387,"num":45,"pourcentage":0.5690938275207938,"vote":39,"name":"قائمة حركة الشعب الوحدوية التقدمية"},"56":{"id":387,"num":45,"pourcentage":0.3524436090225564,"vote":15,"name":"قائمة حركة الشعب الوحدوية التقدمية"},"57":{"id":387,"num":45,"pourcentage":0.4933288485256195,"vote":44,"name":"قائمة حركة الشعب الوحدوية التقدمية"},"58":{"id":387,"num":45,"pourcentage":4.724000692161274,"vote":273,"name":"قائمة حركة الشعب الوحدوية التقدمية"},"59":{"id":387,"num":45,"pourcentage":0.35921525283227407,"vote":13,"name":"قائمة حركة الشعب الوحدوية التقدمية"},"60":{"id":387,"num":45,"pourcentage":1.466582861931699,"vote":70,"name":"قائمة حركة الشعب الوحدوية التقدمية"},"61":{"id":387,"num":45,"pourcentage":0.5521650682941005,"vote":19,"name":"قائمة حركة الشعب الوحدوية التقدمية"}},"392":{"51":{"id":392,"num":12,"pourcentage":0.5242801890846583,"vote":61,"name":"قائمة حركة الوحدة الشعبية"},"52":{"id":392,"num":12,"pourcentage":0.41680748000450607,"vote":37,"name":"قائمة حركة الوحدة الشعبية"},"53":{"id":392,"num":12,"pourcentage":0.9055425448868072,"vote":58,"name":"قائمة حركة الوحدة الشعبية"},"54":{"id":392,"num":12,"pourcentage":0.6648289281660451,"vote":41,"name":"قائمة حركة الوحدة الشعبية"},"55":{"id":392,"num":12,"pourcentage":0.7150153217568949,"vote":49,"name":"قائمة حركة الوحدة الشعبية"},"56":{"id":392,"num":12,"pourcentage":0.8458646616541353,"vote":36,"name":"قائمة حركة الوحدة الشعبية"},"57":{"id":392,"num":12,"pourcentage":0.3924206749635609,"vote":35,"name":"قائمة حركة الوحدة الشعبية"},"58":{"id":392,"num":12,"pourcentage":0.5710330507008133,"vote":33,"name":"قائمة حركة الوحدة الشعبية"},"59":{"id":392,"num":12,"pourcentage":0.6907985631389887,"vote":25,"name":"قائمة حركة الوحدة الشعبية"},"60":{"id":392,"num":12,"pourcentage":0.754242614707731,"vote":36,"name":"قائمة حركة الوحدة الشعبية"},"61":{"id":392,"num":12,"pourcentage":0.4068584713746004,"vote":14,"name":"قائمة حركة الوحدة الشعبية"}},"394":{"51":{"id":394,"num":27,"pourcentage":4.254404813064031,"vote":495,"name":"قائمة حركة الوطنيون الديمقراطيون"},"52":{"id":394,"num":27,"pourcentage":3.525965979497578,"vote":313,"name":"قائمة حركة الوطنيون الديمقراطيون"},"53":{"id":394,"num":27,"pourcentage":0.6557377049180327,"vote":42,"name":"قائمة حركة الوطنيون الديمقراطيون"},"54":{"id":394,"num":27,"pourcentage":1.4431652343116588,"vote":89,"name":"قائمة حركة الوطنيون الديمقراطيون"},"55":{"id":394,"num":27,"pourcentage":2.539033999708157,"vote":174,"name":"قائمة حركة الوطنيون الديمقراطيون"},"56":{"id":394,"num":27,"pourcentage":1.668233082706767,"vote":71,"name":"قائمة حركة الوطنيون الديمقراطيون"},"57":{"id":394,"num":27,"pourcentage":1.8051351048323803,"vote":161,"name":"قائمة حركة الوطنيون الديمقراطيون"},"58":{"id":394,"num":27,"pourcentage":0.709465305416162,"vote":41,"name":"قائمة حركة الوطنيون الديمقراطيون"},"59":{"id":394,"num":27,"pourcentage":2.5697706548770376,"vote":93,"name":"قائمة حركة الوطنيون الديمقراطيون"},"60":{"id":394,"num":27,"pourcentage":4.420699769536979,"vote":211,"name":"قائمة حركة الوطنيون الديمقراطيون"},"61":{"id":394,"num":27,"pourcentage":0.6393490264458007,"vote":22,"name":"قائمة حركة الوطنيون الديمقراطيون"}},"400":{"51":{"id":400,"num":21,"pourcentage":0.7735281478298238,"vote":90,"name":"قائمة حرية وعمل"},"52":{"id":400,"num":21,"pourcentage":0.7547594908189703,"vote":67,"name":"قائمة حرية وعمل"},"53":{"id":400,"num":21,"pourcentage":0.3434816549570648,"vote":22,"name":"قائمة حرية وعمل"},"54":{"id":400,"num":21,"pourcentage":0.6323982487433112,"vote":39,"name":"قائمة حرية وعمل"},"55":{"id":400,"num":21,"pourcentage":0.4815409309791332,"vote":33,"name":"قائمة حرية وعمل"},"56":{"id":400,"num":21,"pourcentage":0.681390977443609,"vote":29,"name":"قائمة حرية وعمل"},"57":{"id":400,"num":21,"pourcentage":0.1906043278394439,"vote":17,"name":"قائمة حرية وعمل"},"58":{"id":400,"num":21,"pourcentage":0.5364249870219762,"vote":31,"name":"قائمة حرية وعمل"},"59":{"id":400,"num":21,"pourcentage":0.5526388505111909,"vote":20,"name":"قائمة حرية وعمل"},"60":{"id":400,"num":21,"pourcentage":0.6075843285145611,"vote":29,"name":"قائمة حرية وعمل"},"61":{"id":400,"num":21,"pourcentage":0.34873583260680036,"vote":12,"name":"قائمة حرية وعمل"}},"418":{"51":{"id":418,"num":4,"pourcentage":0.4211431027073485,"vote":49,"name":"قائمة حزب الانفتاح والوفاء"},"52":{"id":418,"num":4,"pourcentage":0.43933761405880367,"vote":39,"name":"قائمة حزب الانفتاح والوفاء"},"53":{"id":418,"num":4,"pourcentage":0.4215456674473068,"vote":27,"name":"قائمة حزب الانفتاح والوفاء"},"54":{"id":418,"num":4,"pourcentage":0.40538349278417385,"vote":25,"name":"قائمة حزب الانفتاح والوفاء"},"55":{"id":418,"num":4,"pourcentage":0.33561943674303224,"vote":23,"name":"قائمة حزب الانفتاح والوفاء"},"56":{"id":418,"num":4,"pourcentage":0.4699248120300752,"vote":20,"name":"قائمة حزب الانفتاح والوفاء"},"57":{"id":418,"num":4,"pourcentage":0.6951451956497365,"vote":62,"name":"قائمة حزب الانفتاح والوفاء"},"58":{"id":418,"num":4,"pourcentage":0.9344177193286035,"vote":54,"name":"قائمة حزب الانفتاح والوفاء"},"59":{"id":418,"num":4,"pourcentage":0.7460624481901078,"vote":27,"name":"قائمة حزب الانفتاح والوفاء"},"60":{"id":418,"num":4,"pourcentage":0.6913890634820867,"vote":33,"name":"قائمة حزب الانفتاح والوفاء"},"61":{"id":418,"num":4,"pourcentage":0.6393490264458007,"vote":22,"name":"قائمة حزب الانفتاح والوفاء"}},"423":{"51":{"id":423,"num":17,"pourcentage":0.5758487322733132,"vote":67,"name":"قائمة حزب الحرية والتنمية"},"52":{"id":423,"num":17,"pourcentage":0.6871690886560775,"vote":61,"name":"قائمة حزب الحرية والتنمية"},"53":{"id":423,"num":17,"pourcentage":0.624512099921936,"vote":40,"name":"قائمة حزب الحرية والتنمية"},"54":{"id":423,"num":17,"pourcentage":0.7134749473001459,"vote":44,"name":"قائمة حزب الحرية والتنمية"},"55":{"id":423,"num":17,"pourcentage":0.8171603677221655,"vote":56,"name":"قائمة حزب الحرية والتنمية"},"56":{"id":423,"num":17,"pourcentage":0.5874060150375939,"vote":25,"name":"قائمة حزب الحرية والتنمية"},"57":{"id":423,"num":17,"pourcentage":0.9193855813431999,"vote":82,"name":"قائمة حزب الحرية والتنمية"},"58":{"id":423,"num":17,"pourcentage":2.9416854127011596,"vote":170,"name":"قائمة حزب الحرية والتنمية"},"59":{"id":423,"num":17,"pourcentage":0.8013263332412269,"vote":29,"name":"قائمة حزب الحرية والتنمية"},"60":{"id":423,"num":17,"pourcentage":0.8799497171590195,"vote":42,"name":"قائمة حزب الحرية والتنمية"},"61":{"id":423,"num":17,"pourcentage":0.7265329845975007,"vote":25,"name":"قائمة حزب الحرية والتنمية"}},"426":{"51":{"id":426,"num":24,"pourcentage":0.44692737430167595,"vote":52,"name":"قائمة حزب التحالف الوطني للسلم والنماء"},"52":{"id":426,"num":24,"pourcentage":0.37174721189591076,"vote":33,"name":"قائمة حزب التحالف الوطني للسلم والنماء"},"53":{"id":426,"num":24,"pourcentage":1.2646370023419204,"vote":81,"name":"قائمة حزب التحالف الوطني للسلم والنماء"},"54":{"id":426,"num":24,"pourcentage":0.32430679422733905,"vote":20,"name":"قائمة حزب التحالف الوطني للسلم والنماء"},"55":{"id":426,"num":24,"pourcentage":0.9776740113818766,"vote":67,"name":"قائمة حزب التحالف الوطني للسلم والنماء"},"56":{"id":426,"num":24,"pourcentage":0.5639097744360901,"vote":24,"name":"قائمة حزب التحالف الوطني للسلم والنماء"},"57":{"id":426,"num":24,"pourcentage":0.34757259782486827,"vote":31,"name":"قائمة حزب التحالف الوطني للسلم والنماء"},"58":{"id":426,"num":24,"pourcentage":0.39799273230662746,"vote":23,"name":"قائمة حزب التحالف الوطني للسلم والنماء"},"59":{"id":426,"num":24,"pourcentage":0.33158331030671456,"vote":12,"name":"قائمة حزب التحالف الوطني للسلم والنماء"},"60":{"id":426,"num":24,"pourcentage":0.4818772260632726,"vote":23,"name":"قائمة حزب التحالف الوطني للسلم والنماء"},"61":{"id":426,"num":24,"pourcentage":0.23249055507120026,"vote":8,"name":"قائمة حزب التحالف الوطني للسلم والنماء"}},"430":{"51":{"id":430,"num":5,"pourcentage":2.8276751181779116,"vote":329,"name":"قائمة حزب التكتل الديمقراطي من أجل العمل والحريات"},"52":{"id":430,"num":5,"pourcentage":2.3431339416469528,"vote":208,"name":"قائمة حزب التكتل الديمقراطي من أجل العمل والحريات"},"53":{"id":430,"num":5,"pourcentage":2.1233411397345825,"vote":136,"name":"قائمة حزب التكتل الديمقراطي من أجل العمل والحريات"},"54":{"id":430,"num":5,"pourcentage":3.1619912437165563,"vote":195,"name":"قائمة حزب التكتل الديمقراطي من أجل العمل والحريات"},"55":{"id":430,"num":5,"pourcentage":7.558733401430031,"vote":518,"name":"قائمة حزب التكتل الديمقراطي من أجل العمل والحريات"},"56":{"id":430,"num":5,"pourcentage":1.6917293233082706,"vote":72,"name":"قائمة حزب التكتل الديمقراطي من أجل العمل والحريات"},"57":{"id":430,"num":5,"pourcentage":4.114811077475053,"vote":367,"name":"قائمة حزب التكتل الديمقراطي من أجل العمل والحريات"},"58":{"id":430,"num":5,"pourcentage":1.8169233431389515,"vote":105,"name":"قائمة حزب التكتل الديمقراطي من أجل العمل والحريات"},"59":{"id":430,"num":5,"pourcentage":3.0671456203371097,"vote":111,"name":"قائمة حزب التكتل الديمقراطي من أجل العمل والحريات"},"60":{"id":430,"num":5,"pourcentage":8.233815210559396,"vote":393,"name":"قائمة حزب التكتل الديمقراطي من أجل العمل والحريات"},"61":{"id":430,"num":5,"pourcentage":2.2377215925603022,"vote":77,"name":"قائمة حزب التكتل الديمقراطي من أجل العمل والحريات"}},"433":{"51":{"id":433,"num":42,"pourcentage":0.7391491190373872,"vote":86,"name":"قائمة حزب العدالة والتنمية (تونس لكل التونسين)"},"52":{"id":433,"num":42,"pourcentage":0.777289624873268,"vote":69,"name":"قائمة حزب العدالة والتنمية (تونس لكل التونسين)"},"53":{"id":433,"num":42,"pourcentage":0.4839968774395004,"vote":31,"name":"قائمة حزب العدالة والتنمية (تونس لكل التونسين)"},"54":{"id":433,"num":42,"pourcentage":0.6648289281660451,"vote":41,"name":"قائمة حزب العدالة والتنمية (تونس لكل التونسين)"},"55":{"id":433,"num":42,"pourcentage":0.6858310229096746,"vote":47,"name":"قائمة حزب العدالة والتنمية (تونس لكل التونسين)"},"56":{"id":433,"num":42,"pourcentage":0.5404135338345865,"vote":23,"name":"قائمة حزب العدالة والتنمية (تونس لكل التونسين)"},"57":{"id":433,"num":42,"pourcentage":1.7827110662630339,"vote":159,"name":"قائمة حزب العدالة والتنمية (تونس لكل التونسين)"},"58":{"id":433,"num":42,"pourcentage":1.3151064197958124,"vote":76,"name":"قائمة حزب العدالة والتنمية (تونس لكل التونسين)"},"59":{"id":433,"num":42,"pourcentage":0.8013263332412269,"vote":29,"name":"قائمة حزب العدالة والتنمية (تونس لكل التونسين)"},"60":{"id":433,"num":42,"pourcentage":0.5866331447726797,"vote":28,"name":"قائمة حزب العدالة والتنمية (تونس لكل التونسين)"},"61":{"id":433,"num":42,"pourcentage":0.3777971519907004,"vote":13,"name":"قائمة حزب العدالة والتنمية (تونس لكل التونسين)"}},"437":{"51":{"id":437,"num":25,"pourcentage":2.922217447357112,"vote":340,"name":"قائمة حزب العمال الشيوعي التونسي (البديل الثوري)"},"52":{"id":437,"num":25,"pourcentage":2.883857158950096,"vote":256,"name":"قائمة حزب العمال الشيوعي التونسي (البديل الثوري)"},"53":{"id":437,"num":25,"pourcentage":10.913348946135832,"vote":699,"name":"قائمة حزب العمال الشيوعي التونسي (البديل الثوري)"},"54":{"id":437,"num":25,"pourcentage":7.929301118858439,"vote":489,"name":"قائمة حزب العمال الشيوعي التونسي (البديل الثوري)"},"55":{"id":437,"num":25,"pourcentage":4.319276229388589,"vote":296,"name":"قائمة حزب العمال الشيوعي التونسي (البديل الثوري)"},"56":{"id":437,"num":25,"pourcentage":4.041353383458646,"vote":172,"name":"قائمة حزب العمال الشيوعي التونسي (البديل الثوري)"},"57":{"id":437,"num":25,"pourcentage":2.4778562619127706,"vote":221,"name":"قائمة حزب العمال الشيوعي التونسي (البديل الثوري)"},"58":{"id":437,"num":25,"pourcentage":2.3014362346426718,"vote":133,"name":"قائمة حزب العمال الشيوعي التونسي (البديل الثوري)"},"59":{"id":437,"num":25,"pourcentage":3.0118817352859906,"vote":109,"name":"قائمة حزب العمال الشيوعي التونسي (البديل الثوري)"},"60":{"id":437,"num":25,"pourcentage":2.6608003352189398,"vote":127,"name":"قائمة حزب العمال الشيوعي التونسي (البديل الثوري)"},"61":{"id":437,"num":25,"pourcentage":29.41005521650683,"vote":1012,"name":"قائمة حزب العمال الشيوعي التونسي (البديل الثوري)"}},"438":{"51":{"id":438,"num":20,"pourcentage":0.9969918349806617,"vote":116,"name":"قائمة حزب العمل التونسي"},"52":{"id":438,"num":20,"pourcentage":0.597048552438887,"vote":53,"name":"قائمة حزب العمل التونسي"},"53":{"id":438,"num":20,"pourcentage":2.0921155347384857,"vote":134,"name":"قائمة حزب العمل التونسي"},"54":{"id":438,"num":20,"pourcentage":0.5026755310523755,"vote":31,"name":"قائمة حزب العمل التونسي"},"55":{"id":438,"num":20,"pourcentage":0.5836859769444039,"vote":40,"name":"قائمة حزب العمل التونسي"},"56":{"id":438,"num":20,"pourcentage":1.4802631578947367,"vote":63,"name":"قائمة حزب العمل التونسي"},"57":{"id":438,"num":20,"pourcentage":0.31393653997084875,"vote":28,"name":"قائمة حزب العمل التونسي"},"58":{"id":438,"num":20,"pourcentage":0.46720885966430176,"vote":27,"name":"قائمة حزب العمل التونسي"},"59":{"id":438,"num":20,"pourcentage":1.5750207239568943,"vote":57,"name":"قائمة حزب العمل التونسي"},"60":{"id":438,"num":20,"pourcentage":1.152315105803478,"vote":55,"name":"قائمة حزب العمل التونسي"},"61":{"id":438,"num":20,"pourcentage":0.8718395815170008,"vote":30,"name":"قائمة حزب العمل التونسي"}},"444":{"51":{"id":444,"num":2,"pourcentage":0.35238504512247526,"vote":41,"name":"قائمة الحزب الليبرالي المغاربي"},"52":{"id":444,"num":2,"pourcentage":1.0363861664976908,"vote":92,"name":"قائمة الحزب الليبرالي المغاربي"},"53":{"id":444,"num":2,"pourcentage":0.5620608899297423,"vote":36,"name":"قائمة الحزب الليبرالي المغاربي"},"54":{"id":444,"num":2,"pourcentage":0.5675368898978433,"vote":35,"name":"قائمة الحزب الليبرالي المغاربي"},"55":{"id":444,"num":2,"pourcentage":0.4669487815555231,"vote":32,"name":"قائمة الحزب الليبرالي المغاربي"},"56":{"id":444,"num":2,"pourcentage":0.7283834586466165,"vote":31,"name":"قائمة الحزب الليبرالي المغاربي"},"57":{"id":444,"num":2,"pourcentage":0.44848077138692677,"vote":40,"name":"قائمة الحزب الليبرالي المغاربي"},"58":{"id":444,"num":2,"pourcentage":0.5364249870219762,"vote":31,"name":"قائمة الحزب الليبرالي المغاربي"},"59":{"id":444,"num":2,"pourcentage":0.7460624481901078,"vote":27,"name":"قائمة الحزب الليبرالي المغاربي"},"60":{"id":444,"num":2,"pourcentage":0.5866331447726797,"vote":28,"name":"قائمة الحزب الليبرالي المغاربي"},"61":{"id":444,"num":2,"pourcentage":0.2034292356873002,"vote":7,"name":"قائمة الحزب الليبرالي المغاربي"}},"446":{"51":{"id":446,"num":1,"pourcentage":5.646755479157714,"vote":657,"name":"قائمة حزب المؤتمر من أجل الجمهورية"},"52":{"id":446,"num":1,"pourcentage":5.260786301678495,"vote":467,"name":"قائمة حزب المؤتمر من أجل الجمهورية"},"53":{"id":446,"num":1,"pourcentage":5.105386416861827,"vote":327,"name":"قائمة حزب المؤتمر من أجل الجمهورية"},"54":{"id":446,"num":1,"pourcentage":5.85373763580347,"vote":361,"name":"قائمة حزب المؤتمر من أجل الجمهورية"},"55":{"id":446,"num":1,"pourcentage":4.640303516708011,"vote":318,"name":"قائمة حزب المؤتمر من أجل الجمهورية"},"56":{"id":446,"num":1,"pourcentage":3.31296992481203,"vote":141,"name":"قائمة حزب المؤتمر من أجل الجمهورية"},"57":{"id":446,"num":1,"pourcentage":3.4308779011099895,"vote":306,"name":"قائمة حزب المؤتمر من أجل الجمهورية"},"58":{"id":446,"num":1,"pourcentage":3.028205571898252,"vote":175,"name":"قائمة حزب المؤتمر من أجل الجمهورية"},"59":{"id":446,"num":1,"pourcentage":4.006631666206134,"vote":145,"name":"قائمة حزب المؤتمر من أجل الجمهورية"},"60":{"id":446,"num":1,"pourcentage":9.93086109365179,"vote":474,"name":"قائمة حزب المؤتمر من أجل الجمهورية"},"61":{"id":446,"num":1,"pourcentage":2.5864574251671026,"vote":89,"name":"قائمة حزب المؤتمر من أجل الجمهورية"}},"453":{"51":{"id":453,"num":22,"pourcentage":0.12892135797163728,"vote":15,"name":"قائمة حزب المستقبل من أجل التنمية والديمقراطية"},"52":{"id":453,"num":22,"pourcentage":0.23656640757012504,"vote":21,"name":"قائمة حزب المستقبل من أجل التنمية والديمقراطية"},"53":{"id":453,"num":22,"pourcentage":0.2810304449648712,"vote":18,"name":"قائمة حزب المستقبل من أجل التنمية والديمقراطية"},"54":{"id":453,"num":22,"pourcentage":0.3729528133614399,"vote":23,"name":"قائمة حزب المستقبل من أجل التنمية والديمقراطية"},"55":{"id":453,"num":22,"pourcentage":0.29184298847220197,"vote":20,"name":"قائمة حزب المستقبل من أجل التنمية والديمقراطية"},"56":{"id":453,"num":22,"pourcentage":0.30545112781954886,"vote":13,"name":"قائمة حزب المستقبل من أجل التنمية والديمقراطية"},"57":{"id":453,"num":22,"pourcentage":0.6166610606570243,"vote":55,"name":"قائمة حزب المستقبل من أجل التنمية والديمقراطية"},"58":{"id":453,"num":22,"pourcentage":0.8132894964526735,"vote":47,"name":"قائمة حزب المستقبل من أجل التنمية والديمقراطية"},"59":{"id":453,"num":22,"pourcentage":0.33158331030671456,"vote":12,"name":"قائمة حزب المستقبل من أجل التنمية والديمقراطية"},"60":{"id":453,"num":22,"pourcentage":0.3771213073538655,"vote":18,"name":"قائمة حزب المستقبل من أجل التنمية والديمقراطية"},"61":{"id":453,"num":22,"pourcentage":0.2034292356873002,"vote":7,"name":"قائمة حزب المستقبل من أجل التنمية والديمقراطية"}},"455":{"51":{"id":455,"num":11,"pourcentage":0.6360120326600773,"vote":74,"name":"قائمة حزب النضال التقدمي"},"52":{"id":455,"num":11,"pourcentage":0.6646389546017799,"vote":59,"name":"قائمة حزب النضال التقدمي"},"53":{"id":455,"num":11,"pourcentage":0.4371584699453552,"vote":28,"name":"قائمة حزب النضال التقدمي"},"54":{"id":455,"num":11,"pourcentage":0.5188908707637425,"vote":32,"name":"قائمة حزب النضال التقدمي"},"55":{"id":455,"num":11,"pourcentage":2.247191011235955,"vote":154,"name":"قائمة حزب النضال التقدمي"},"56":{"id":455,"num":11,"pourcentage":2.7490601503759398,"vote":117,"name":"قائمة حزب النضال التقدمي"},"57":{"id":455,"num":11,"pourcentage":0.2130283664087902,"vote":19,"name":"قائمة حزب النضال التقدمي"},"58":{"id":455,"num":11,"pourcentage":0.7786814327738363,"vote":45,"name":"قائمة حزب النضال التقدمي"},"59":{"id":455,"num":11,"pourcentage":0.44211108040895275,"vote":16,"name":"قائمة حزب النضال التقدمي"},"60":{"id":455,"num":11,"pourcentage":0.7332914309658495,"vote":35,"name":"قائمة حزب النضال التقدمي"},"61":{"id":455,"num":11,"pourcentage":0.31967451322290036,"vote":11,"name":"قائمة حزب النضال التقدمي"}},"457":{"51":{"id":457,"num":9,"pourcentage":0.30081650193382037,"vote":35,"name":"قائمة حزب الوسط الاجتماعي"},"52":{"id":457,"num":9,"pourcentage":0.34921707784161315,"vote":31,"name":"قائمة حزب الوسط الاجتماعي"},"53":{"id":457,"num":9,"pourcentage":0.2654176424668228,"vote":17,"name":"قائمة حزب الوسط الاجتماعي"},"54":{"id":457,"num":9,"pourcentage":0.43781417220690777,"vote":27,"name":"قائمة حزب الوسط الاجتماعي"},"55":{"id":457,"num":9,"pourcentage":0.3648037355902524,"vote":25,"name":"قائمة حزب الوسط الاجتماعي"},"56":{"id":457,"num":9,"pourcentage":0.775375939849624,"vote":33,"name":"قائمة حزب الوسط الاجتماعي"},"57":{"id":457,"num":9,"pourcentage":0.7175692342190829,"vote":64,"name":"قائمة حزب الوسط الاجتماعي"},"58":{"id":457,"num":9,"pourcentage":1.003633846686278,"vote":58,"name":"قائمة حزب الوسط الاجتماعي"},"59":{"id":457,"num":9,"pourcentage":0.46974302293451226,"vote":17,"name":"قائمة حزب الوسط الاجتماعي"},"60":{"id":457,"num":9,"pourcentage":0.16760946993505133,"vote":8,"name":"قائمة حزب الوسط الاجتماعي"},"61":{"id":457,"num":9,"pourcentage":0.34873583260680036,"vote":12,"name":"قائمة حزب الوسط الاجتماعي"}},"459":{"51":{"id":459,"num":10,"pourcentage":0.24924795874516542,"vote":29,"name":"قائمة حزب الوفاق الجمهوري"},"52":{"id":459,"num":10,"pourcentage":0.4843978821673989,"vote":43,"name":"قائمة حزب الوفاق الجمهوري"},"53":{"id":459,"num":10,"pourcentage":1.4988290398126463,"vote":96,"name":"قائمة حزب الوفاق الجمهوري"},"54":{"id":459,"num":10,"pourcentage":0.25944543538187126,"vote":16,"name":"قائمة حزب الوفاق الجمهوري"},"55":{"id":459,"num":10,"pourcentage":0.4961330804027433,"vote":34,"name":"قائمة حزب الوفاق الجمهوري"},"56":{"id":459,"num":10,"pourcentage":0.6109022556390977,"vote":26,"name":"قائمة حزب الوفاق الجمهوري"},"57":{"id":459,"num":10,"pourcentage":0.4709048099562731,"vote":42,"name":"قائمة حزب الوفاق الجمهوري"},"58":{"id":459,"num":10,"pourcentage":0.7613774009344177,"vote":44,"name":"قائمة حزب الوفاق الجمهوري"},"59":{"id":459,"num":10,"pourcentage":1.160541586073501,"vote":42,"name":"قائمة حزب الوفاق الجمهوري"},"60":{"id":459,"num":10,"pourcentage":0.4818772260632726,"vote":23,"name":"قائمة حزب الوفاق الجمهوري"},"61":{"id":459,"num":10,"pourcentage":0.5812263876780006,"vote":20,"name":"قائمة حزب الوفاق الجمهوري"}},"464":{"51":{"id":464,"num":19,"pourcentage":26.30855178341212,"vote":3061,"name":"قائمة حركة النهضة"},"52":{"id":464,"num":19,"pourcentage":29.537005745184185,"vote":2622,"name":"قائمة حركة النهضة"},"53":{"id":464,"num":19,"pourcentage":32.068696330991415,"vote":2054,"name":"قائمة حركة النهضة"},"54":{"id":464,"num":19,"pourcentage":30.338900599967573,"vote":1871,"name":"قائمة حركة النهضة"},"55":{"id":464,"num":19,"pourcentage":24.806654020137167,"vote":1700,"name":"قائمة حركة النهضة"},"56":{"id":464,"num":19,"pourcentage":20.6296992481203,"vote":878,"name":"قائمة حركة النهضة"},"57":{"id":464,"num":19,"pourcentage":40.25114923197668,"vote":3590,"name":"قائمة حركة النهضة"},"58":{"id":464,"num":19,"pourcentage":22.702889773317185,"vote":1312,"name":"قائمة حركة النهضة"},"59":{"id":464,"num":19,"pourcentage":22.243713733075435,"vote":805,"name":"قائمة حركة النهضة"},"60":{"id":464,"num":19,"pourcentage":25.288078776450867,"vote":1207,"name":"قائمة حركة النهضة"},"61":{"id":464,"num":19,"pourcentage":30.078465562336532,"vote":1035,"name":"قائمة حركة النهضة"}},"479":{"51":{"id":479,"num":40,"pourcentage":2.019767941555651,"vote":235,"name":"قائمة سنابل بلادي"},"52":{"id":479,"num":40,"pourcentage":1.3180128421764108,"vote":117,"name":"قائمة سنابل بلادي"},"53":{"id":479,"num":40,"pourcentage":0.4527712724434036,"vote":29,"name":"قائمة سنابل بلادي"},"54":{"id":479,"num":40,"pourcentage":1.2485811577752552,"vote":77,"name":"قائمة سنابل بلادي"},"55":{"id":479,"num":40,"pourcentage":0.6420545746388443,"vote":44,"name":"قائمة سنابل بلادي"},"56":{"id":479,"num":40,"pourcentage":0.4464285714285714,"vote":19,"name":"قائمة سنابل بلادي"},"57":{"id":479,"num":40,"pourcentage":0.44848077138692677,"vote":40,"name":"قائمة سنابل بلادي"},"58":{"id":479,"num":40,"pourcentage":0.3633846686277903,"vote":21,"name":"قائمة سنابل بلادي"},"59":{"id":479,"num":40,"pourcentage":0.5802707930367506,"vote":21,"name":"قائمة سنابل بلادي"},"60":{"id":479,"num":40,"pourcentage":0.9218520846427822,"vote":44,"name":"قائمة سنابل بلادي"},"61":{"id":479,"num":40,"pourcentage":0.34873583260680036,"vote":12,"name":"قائمة سنابل بلادي"}},"480":{"51":{"id":480,"num":38,"pourcentage":0.7133648474430597,"vote":83,"name":"قائمة سواعد المستقبل"},"52":{"id":480,"num":38,"pourcentage":0.7885546919004168,"vote":70,"name":"قائمة سواعد المستقبل"},"53":{"id":480,"num":38,"pourcentage":0.6869633099141296,"vote":44,"name":"قائمة سواعد المستقبل"},"54":{"id":480,"num":38,"pourcentage":0.6486135884546781,"vote":40,"name":"قائمة سواعد المستقبل"},"55":{"id":480,"num":38,"pourcentage":1.0068583102290969,"vote":69,"name":"قائمة سواعد المستقبل"},"56":{"id":480,"num":38,"pourcentage":0.7518796992481203,"vote":32,"name":"قائمة سواعد المستقبل"},"57":{"id":480,"num":38,"pourcentage":0.2690884628321561,"vote":24,"name":"قائمة سواعد المستقبل"},"58":{"id":480,"num":38,"pourcentage":0.622945146219069,"vote":36,"name":"قائمة سواعد المستقبل"},"59":{"id":480,"num":38,"pourcentage":0.7460624481901078,"vote":27,"name":"قائمة سواعد المستقبل"},"60":{"id":480,"num":38,"pourcentage":0.7123402472239682,"vote":34,"name":"قائمة سواعد المستقبل"},"61":{"id":480,"num":38,"pourcentage":0.26155187445510025,"vote":9,"name":"قائمة سواعد المستقبل"}},"500":{"51":{"id":500,"num":30,"pourcentage":8.904168457241083,"vote":1036,"name":"قائمة العريضة الشعبية للحرية والعدالة والتنمية"},"52":{"id":500,"num":30,"pourcentage":8.5389208065788,"vote":758,"name":"قائمة العريضة الشعبية للحرية والعدالة والتنمية"},"53":{"id":500,"num":30,"pourcentage":7.259953161592506,"vote":465,"name":"قائمة العريضة الشعبية للحرية والعدالة والتنمية"},"54":{"id":500,"num":30,"pourcentage":10.523755472677152,"vote":649,"name":"قائمة العريضة الشعبية للحرية والعدالة والتنمية"},"55":{"id":500,"num":30,"pourcentage":13.24967167663797,"vote":908,"name":"قائمة العريضة الشعبية للحرية والعدالة والتنمية"},"56":{"id":500,"num":30,"pourcentage":11.30169172932331,"vote":481,"name":"قائمة العريضة الشعبية للحرية والعدالة والتنمية"},"57":{"id":500,"num":30,"pourcentage":5.000560600964234,"vote":446,"name":"قائمة العريضة الشعبية للحرية والعدالة والتنمية"},"58":{"id":500,"num":30,"pourcentage":6.956220799446271,"vote":402,"name":"قائمة العريضة الشعبية للحرية والعدالة والتنمية"},"59":{"id":500,"num":30,"pourcentage":15.169936446532192,"vote":549,"name":"قائمة العريضة الشعبية للحرية والعدالة والتنمية"},"60":{"id":500,"num":30,"pourcentage":9.490886235072281,"vote":453,"name":"قائمة العريضة الشعبية للحرية والعدالة والتنمية"},"61":{"id":500,"num":30,"pourcentage":2.383028189479802,"vote":82,"name":"قائمة العريضة الشعبية للحرية والعدالة والتنمية"}},"552":{"51":{"id":552,"num":18,"pourcentage":3.6957455951869362,"vote":430,"name":"قائمة مستقلة من أجل التشغيل"},"52":{"id":552,"num":18,"pourcentage":4.6862678832939055,"vote":416,"name":"قائمة مستقلة من أجل التشغيل"},"53":{"id":552,"num":18,"pourcentage":3.02888368462139,"vote":194,"name":"قائمة مستقلة من أجل التشغيل"},"54":{"id":552,"num":18,"pourcentage":5.26998540619426,"vote":325,"name":"قائمة مستقلة من أجل التشغيل"},"55":{"id":552,"num":18,"pourcentage":5.676346125784328,"vote":389,"name":"قائمة مستقلة من أجل التشغيل"},"56":{"id":552,"num":18,"pourcentage":5.68609022556391,"vote":242,"name":"قائمة مستقلة من أجل التشغيل"},"57":{"id":552,"num":18,"pourcentage":2.219979818365288,"vote":198,"name":"قائمة مستقلة من أجل التشغيل"},"58":{"id":552,"num":18,"pourcentage":3.979927323066274,"vote":230,"name":"قائمة مستقلة من أجل التشغيل"},"59":{"id":552,"num":18,"pourcentage":9.256700746062448,"vote":335,"name":"قائمة مستقلة من أجل التشغيل"},"60":{"id":552,"num":18,"pourcentage":4.1064320134087575,"vote":196,"name":"قائمة مستقلة من أجل التشغيل"},"61":{"id":552,"num":18,"pourcentage":1.2205754141238012,"vote":42,"name":"قائمة مستقلة من أجل التشغيل"}}}